ape_hardhat/__init__.py
ape_hardhat/exceptions.py
ape_hardhat/provider.py
ape_hardhat/py.typed
ape_hardhat/version.py
ape_hardhat-0.8.4.dist-info/LICENSE
ape_hardhat-0.8.4.dist-info/METADATA
ape_hardhat-0.8.4.dist-info/WHEEL
ape_hardhat-0.8.4.dist-info/top_level.txt
ape_hardhat-0.8.4.dist-info/RECORD
