Metadata-Version: 2.1
Name: ape-hardhat
Version: 0.8.4
Summary: ape-hardhat: Ape network provider for Hardhat
Home-page: https://github.com/ApeWorX/ape-hardhat
Author: ApeWorX Ltd.
Author-email: admin@apeworx.io
License: Apache-2.0
Keywords: ethereum
Classifier: Development Status :: 5 - Production/Stable
Classifier: Intended Audience :: Developers
Classifier: License :: OSI Approved :: MIT License
Classifier: Natural Language :: English
Classifier: Operating System :: MacOS
Classifier: Operating System :: POSIX
Classifier: Programming Language :: Python :: 3
Classifier: Programming Language :: Python :: 3.9
Classifier: Programming Language :: Python :: 3.10
Classifier: Programming Language :: Python :: 3.11
Classifier: Programming Language :: Python :: 3.12
Requires-Python: >=3.8,<4
License-File: LICENSE
Requires-Dist: eth-ape<0.9,>=0.8.10
Requires-Dist: ethpm-types
Requires-Dist: evm-trace
Requires-Dist: web3
Requires-Dist: chompjs<2,>=1.1.9
Requires-Dist: requests
Requires-Dist: hexbytes
Requires-Dist: packaging
Requires-Dist: yarl<2,>=1.9.2
Provides-Extra: test
Requires-Dist: pytest>=6.0; extra == "test"
Requires-Dist: pytest-mock; extra == "test"
Requires-Dist: pytest-xdist; extra == "test"
Requires-Dist: pytest-cov; extra == "test"
Requires-Dist: hypothesis<7.0,>=6.2.0; extra == "test"
Requires-Dist: ape-alchemy; extra == "test"
Requires-Dist: ape-polygon; extra == "test"
Requires-Dist: rich; extra == "test"
Provides-Extra: lint
Requires-Dist: black<25,>=24.10.0; extra == "lint"
Requires-Dist: mypy<2,>=1.13.0; extra == "lint"
Requires-Dist: types-setuptools; extra == "lint"
Requires-Dist: types-requests; extra == "lint"
Requires-Dist: types-PyYAML; extra == "lint"
Requires-Dist: flake8<8,>=7.1.1; extra == "lint"
Requires-Dist: flake8-breakpoint<2,>=1.1.0; extra == "lint"
Requires-Dist: flake8-print<6,>=5.0.0; extra == "lint"
Requires-Dist: flake8-pydantic; extra == "lint"
Requires-Dist: flake8-type-checking; extra == "lint"
Requires-Dist: isort<6,>=5.13.2; extra == "lint"
Requires-Dist: mdformat>=0.7.19; extra == "lint"
Requires-Dist: mdformat-gfm>=0.3.5; extra == "lint"
Requires-Dist: mdformat-frontmatter>=0.4.1; extra == "lint"
Requires-Dist: mdformat-pyproject>=0.0.2; extra == "lint"
Provides-Extra: doc
Requires-Dist: sphinx-ape; extra == "doc"
Provides-Extra: release
Requires-Dist: setuptools>=72.2.0; extra == "release"
Requires-Dist: setuptools-scm; extra == "release"
Requires-Dist: wheel; extra == "release"
Requires-Dist: twine; extra == "release"
Provides-Extra: dev
Requires-Dist: pytest>=6.0; extra == "dev"
Requires-Dist: pytest-mock; extra == "dev"
Requires-Dist: pytest-xdist; extra == "dev"
Requires-Dist: pytest-cov; extra == "dev"
Requires-Dist: hypothesis<7.0,>=6.2.0; extra == "dev"
Requires-Dist: ape-alchemy; extra == "dev"
Requires-Dist: ape-polygon; extra == "dev"
Requires-Dist: rich; extra == "dev"
Requires-Dist: black<25,>=24.10.0; extra == "dev"
Requires-Dist: mypy<2,>=1.13.0; extra == "dev"
Requires-Dist: types-setuptools; extra == "dev"
Requires-Dist: types-requests; extra == "dev"
Requires-Dist: types-PyYAML; extra == "dev"
Requires-Dist: flake8<8,>=7.1.1; extra == "dev"
Requires-Dist: flake8-breakpoint<2,>=1.1.0; extra == "dev"
Requires-Dist: flake8-print<6,>=5.0.0; extra == "dev"
Requires-Dist: flake8-pydantic; extra == "dev"
Requires-Dist: flake8-type-checking; extra == "dev"
Requires-Dist: isort<6,>=5.13.2; extra == "dev"
Requires-Dist: mdformat>=0.7.19; extra == "dev"
Requires-Dist: mdformat-gfm>=0.3.5; extra == "dev"
Requires-Dist: mdformat-frontmatter>=0.4.1; extra == "dev"
Requires-Dist: mdformat-pyproject>=0.0.2; extra == "dev"
Requires-Dist: sphinx-ape; extra == "dev"
Requires-Dist: setuptools>=72.2.0; extra == "dev"
Requires-Dist: setuptools-scm; extra == "dev"
Requires-Dist: wheel; extra == "dev"
Requires-Dist: twine; extra == "dev"
Requires-Dist: commitizen; extra == "dev"
Requires-Dist: pre-commit; extra == "dev"
Requires-Dist: pytest-watch; extra == "dev"
Requires-Dist: IPython; extra == "dev"
Requires-Dist: ipdb; extra == "dev"
